Combinational/carrylookaheadadder.v
module halfadder (s,c,a,b);
output s,c;
input a,b;

assign s=a^b;
assign c=a&b;
endmodule 

module carry_generator(cin,c0,c1,c2,c3,c4,g0,g1,g2,g3,p0,p1,p2,p3);
output c0,c1,c2,c3,c4;
input cin,g0,g1,g2,g3,p0,p1,p2,p3;

assign c0=cin;
assign c1=g0 | (p0&cin);
assign c2=g1 | (p1&g0) | (p1&p0&cin);
assign c3=g2 | (p2&g1) | (p2&p1&g0) | (p2&p1&p0&cin);
assign c4=g3 | (p3&g2) | (p3&p2&g1) | (p3&p2&p1&g0) | (p3&p2&p1&p0&cin);

endmodule

module CLA(a,b,cin,sum,cout);
input[3:0]a,b;
input cin;
output[3:0]sum;
output cout;
wire p0,p1,p2,p3,g0,g1,g2,g3,c1,c2,c3,c4;

halfadder HA1(p0,g0,a[0],b[0]);
halfadder HA2(p1,g1,a[1],b[1]);
halfadder HA3(p2,g2,a[2],b[2]);
halfadder HA4(p3,g3,a[3],b[3]);

carry_generator cg(cin,c0,c1,c2,c3,c4,g0,g1,g2,g3,p0,p1,p2,p3);
assign sum[0]=p0^c0;
assign sum[1]=p1^c1;
assign sum[2]=p2^c2;
assign sum[3]=p3^c3;
assign cout=c4;

endmodule

Combinational/carrylookaheadaddertb.v
module test;
reg[3:0]a,b;
reg cin;
wire cout;
wire [3:0]sum;
//instantiate 
CLA c1(.a(a),
        .b(b),
        .cin(cin),
        .sum(sum),
        .cout(cout));



//clock and reset
                    reg clk,reset;

initial begin
    $dumpfile("cla.vcd");
    $dumpvars(0,test);
    reset=1;
    clk=0;
    #20;
    reset=0;
end
    always begin
        #10 clk = ~clk;
    end           

reg[3:0]i;
always @(posedge clk, posedge reset) 
begin
    if(reset) begin
        i=0;
    end
    else begin
    a<=$random%16;
    b<=$random%16;
    cin<=$random%2;
    #20;
    i=i+1;
    if(i==10)$finish;
    end
    $monitor("%d : a=%b b=%b cin=%b sum=%b cout=%b",$time,a,b,cin,sum,cout);
end
endmodule

Combinational/cla.vcd
$date
	Sun Mar 22 13:31:29 2026
$end
$version
	Icarus Verilog
$end
$timescale
	1s
$end
$scope module test $end
$var wire 4 ! sum [3:0] $end
$var wire 1 " cout $end
$var reg 4 # a [3:0] $end
$var reg 4 $ b [3:0] $end
$var reg 1 % cin $end
$var reg 1 & clk $end
$var reg 4 ' i [3:0] $end
$var reg 1 ( reset $end
$scope module c1 $end
$var wire 4 ) a [3:0] $end
$var wire 4 * b [3:0] $end
$var wire 1 % cin $end
$var wire 1 " cout $end
$var wire 4 + sum [3:0] $end
$var wire 1 , p3 $end
$var wire 1 - p2 $end
$var wire 1 . p1 $end
$var wire 1 / p0 $end
$var wire 1 0 g3 $end
$var wire 1 1 g2 $end
$var wire 1 2 g1 $end
$var wire 1 3 g0 $end
$var wire 1 4 c4 $end
$var wire 1 5 c3 $end
$var wire 1 6 c2 $end
$var wire 1 7 c1 $end
$var wire 1 8 c0 $end
$scope module HA1 $end
$var wire 1 9 a $end
$var wire 1 : b $end
$var wire 1 3 c $end
$var wire 1 / s $end
$upscope $end
$scope module HA2 $end
$var wire 1 ; a $end
$var wire 1 < b $end
$var wire 1 2 c $end
$var wire 1 . s $end
$upscope $end
$scope module HA3 $end
$var wire 1 = a $end
$var wire 1 > b $end
$var wire 1 1 c $end
$var wire 1 - s $end
$upscope $end
$scope module HA4 $end
$var wire 1 ? a $end
$var wire 1 @ b $end
$var wire 1 0 c $end
$var wire 1 , s $end
$upscope $end
$scope module cg $end
$var wire 1 8 c0 $end
$var wire 1 7 c1 $end
$var wire 1 6 c2 $end
$var wire 1 5 c3 $end
$var wire 1 4 c4 $end
$var wire 1 % cin $end
$var wire 1 3 g0 $end
$var wire 1 2 g1 $end
$var wire 1 1 g2 $end
$var wire 1 0 g3 $end
$var wire 1 / p0 $end
$var wire 1 . p1 $end
$var wire 1 - p2 $end
$var wire 1 , p3 $end
$upscope $end
$upscope $end
$upscope $end
$enddefinitions $end
$comment Show the parameter values. $end
$dumpall
$end
#0
$dumpvars
x@
x?
x>
x=
x<
x;
x:
x9
x8
x7
x6
x5
x4
x3
x2
x1
x0
x/
x.
x-
x,
bx +
bx *
bx )
1(
bx '
0&
x%
bx $
bx #
x"
bx !
$end
#10
b0 '
1&
#20
0&
0(
#30
05
0"
04
06
17
b110 !
b110 +
1/
03
0.
02
1-
01
0,
00
1:
0<
0>
0@
09
0;
1=
0?
18
1%
b1 $
b1 *
b100 #
b100 )
1&
#40
0&
#50
1"
14
15
16
b1 !
b1 +
1,
0/
13
1.
1>
1@
19
1;
0=
b1101 $
b1101 *
b11 #
b11 )
1&
b1 '
#60
0&
#70
0"
04
17
b1000 !
b1000 +
1/
03
0,
0:
1<
0>
0@
0;
1=
b10 $
b10 *
b101 #
b101 )
1&
b10 '
#80
0&
#90
1"
14
b100 !
b100 +
0-
11
1,
1>
1?
b110 $
b110 *
b1101 #
b1101 )
1&
b11 '
#100
0&
#110
06
b1010 !
b1010 +
0.
0,
10
0<
1@
b1100 $
b1100 *
1&
b100 '
#120
0&
#130
0"
04
07
1.
00
b1011 !
b1011 +
1:
0@
09
1;
0?
08
0%
b101 $
b101 *
b110 #
b110 )
1&
b101 '
#140
0&
#150
16
b1100 !
b1100 +
17
0/
13
1<
19
0;
b111 $
b111 *
b101 #
b101 )
1&
b110 '
#160
0&
#170
1"
14
07
b1 !
b1 +
1/
03
1-
01
0.
12
1,
0:
0>
1;
1?
b10 $
b10 *
b1111 #
b1111 )
1&
b111 '
#180
0&
#190
05
0"
04
b1101 !
b1101 +
06
02
1:
0<
1>
09
0;
0=
b101 $
b101 *
b1000 #
b1000 )
1&
b1000 '
#200
0&
#210
1"
14
15
17
0,
10
0/
13
0-
11
b1011 !
b1011 +
1@
19
1=
18
1%
b1101 $
b1101 *
b1101 #
b1101 )
1&
b1001 '
#220
0&
#230
1&
b1010 '
